{
  "openapi" : "3.0.1",
  "info" : {
    "title" : "Liferay Commerce Admin Inventory API",
    "description" : "Liferay Commerce Admin Inventory API. A Java client JAR is available for use with the group ID 'com.liferay', artifact ID 'com.liferay.headless.commerce.admin.inventory.client', and version '4.0.38'.",
    "license" : {
      "name" : "Apache 2.0",
      "url" : "http://www.apache.org/licenses/LICENSE-2.0.html"
    },
    "version" : "v1.0"
  },
  "servers" : [ {
    "url" : "http://localhost:8080/o/headless-commerce-admin-inventory/"
  } ],
  "paths" : {
    "/v1.0/warehouse-account-groups/{warehouseAccountGroupId}/account-group" : {
      "get" : {
        "tags" : [ "AccountGroup" ],
        "operationId" : "getWarehouseAccountGroupAccountGroup",
        "parameters" : [ {
          "name" : "warehouseAccountGroupId",
          "in" : "path",
          "required" : true,
          "schema" : {
            "type" : "string"
          }
        } ],
        "responses" : {
          "default" : {
            "description" : "default response",
            "content" : {
              "application/json" : {
                "schema" : {
                  "$ref" : "#/components/schemas/AccountGroup"
                }
              },
              "application/xml" : {
                "schema" : {
                  "$ref" : "#/components/schemas/AccountGroup"
                }
              }
            }
          }
        }
      }
    },
    "/v1.0/warehouse-accounts/{warehouseAccountId}/account" : {
      "get" : {
        "tags" : [ "Account" ],
        "operationId" : "getWarehouseAccountAccount",
        "parameters" : [ {
          "name" : "warehouseAccountId",
          "in" : "path",
          "required" : true,
          "schema" : {
            "type" : "string"
          }
        } ],
        "responses" : {
          "default" : {
            "description" : "default response",
            "content" : {
              "application/json" : {
                "schema" : {
                  "$ref" : "#/components/schemas/Account"
                }
              },
              "application/xml" : {
                "schema" : {
                  "$ref" : "#/components/schemas/Account"
                }
              }
            }
          }
        }
      }
    },
    "/v1.0/warehouse-channels/{warehouseChannelId}/channel" : {
      "get" : {
        "tags" : [ "Channel" ],
        "operationId" : "getWarehouseChannelChannel",
        "parameters" : [ {
          "name" : "warehouseChannelId",
          "in" : "path",
          "required" : true,
          "schema" : {
            "type" : "string"
          }
        } ],
        "responses" : {
          "default" : {
            "description" : "default response",
            "content" : {
              "application/json" : {
                "schema" : {
                  "$ref" : "#/components/schemas/Channel"
                }
              },
              "application/xml" : {
                "schema" : {
                  "$ref" : "#/components/schemas/Channel"
                }
              }
            }
          }
        }
      }
    },
    "/v1.0/openapi.{type}" : {
      "get" : {
        "operationId" : "getOpenAPI",
        "parameters" : [ {
          "name" : "type",
          "in" : "path",
          "required" : true,
          "schema" : {
            "type" : "string"
          }
        } ],
        "responses" : {
          "default" : {
            "description" : "default response",
            "content" : {
              "application/json" : { },
              "application/yaml" : { }
            }
          }
        }
      }
    },
    "/v1.0/warehouse-order-types/{warehouseOrderTypeId}/order-type" : {
      "get" : {
        "tags" : [ "OrderType" ],
        "operationId" : "getWarehouseOrderTypeOrderType",
        "parameters" : [ {
          "name" : "warehouseOrderTypeId",
          "in" : "path",
          "required" : true,
          "schema" : {
            "type" : "string"
          }
        } ],
        "responses" : {
          "default" : {
            "description" : "default response",
            "content" : {
              "application/json" : {
                "schema" : {
                  "$ref" : "#/components/schemas/OrderType"
                }
              },
              "application/xml" : {
                "schema" : {
                  "$ref" : "#/components/schemas/OrderType"
                }
              }
            }
          }
        }
      }
    },
    "/v1.0/replenishment-items/{replenishmentItemId}" : {
      "get" : {
        "tags" : [ "ReplenishmentItem" ],
        "operationId" : "getReplenishmentItem",
        "parameters" : [ {
          "name" : "replenishmentItemId",
          "in" : "path",
          "required" : true,
          "schema" : {
            "type" : "string"
          }
        } ],
        "responses" : {
          "default" : {
            "description" : "default response",
            "content" : {
              "application/json" : {
                "schema" : {
                  "$ref" : "#/components/schemas/ReplenishmentItem"
                }
              },
              "application/xml" : {
                "schema" : {
                  "$ref" : "#/components/schemas/ReplenishmentItem"
                }
              }
            }
          }
        }
      },
      "delete" : {
        "tags" : [ "ReplenishmentItem" ],
        "operationId" : "deleteReplenishmentItem",
        "parameters" : [ {
          "name" : "replenishmentItemId",
          "in" : "path",
          "required" : true,
          "schema" : {
            "type" : "string"
          }
        } ],
        "responses" : {
          "default" : {
            "description" : "default response",
            "content" : {
              "application/json" : { },
              "application/xml" : { }
            }
          }
        }
      },
      "patch" : {
        "tags" : [ "ReplenishmentItem" ],
        "operationId" : "patchReplenishmentItem",
        "parameters" : [ {
          "name" : "replenishmentItemId",
          "in" : "path",
          "required" : true,
          "schema" : {
            "type" : "string"
          }
        } ],
        "requestBody" : {
          "content" : {
            "application/json" : {
              "schema" : {
                "$ref" : "#/components/schemas/ReplenishmentItem"
              }
            },
            "application/xml" : {
              "schema" : {
                "$ref" : "#/components/schemas/ReplenishmentItem"
              }
            }
          }
        },
        "responses" : {
          "default" : {
            "description" : "default response",
            "content" : {
              "application/json" : {
                "schema" : {
                  "$ref" : "#/components/schemas/ReplenishmentItem"
                }
              },
              "application/xml" : {
                "schema" : {
                  "$ref" : "#/components/schemas/ReplenishmentItem"
                }
              }
            }
          }
        }
      }
    },
    "/v1.0/warehouses/{warehouseId}/skus/by-sku/{sku}/replenishment-items" : {
      "post" : {
        "tags" : [ "ReplenishmentItem" ],
        "operationId" : "postReplenishmentItem",
        "parameters" : [ {
          "name" : "warehouseId",
          "in" : "path",
          "required" : true,
          "schema" : {
            "type" : "string"
          }
        }, {
          "name" : "sku",
          "in" : "path",
          "required" : true,
          "schema" : {
            "type" : "string"
          }
        } ],
        "requestBody" : {
          "content" : {
            "application/json" : {
              "schema" : {
                "$ref" : "#/components/schemas/ReplenishmentItem"
              }
            },
            "application/xml" : {
              "schema" : {
                "$ref" : "#/components/schemas/ReplenishmentItem"
              }
            }
          }
        },
        "responses" : {
          "default" : {
            "description" : "default response",
            "content" : {
              "application/json" : {
                "schema" : {
                  "$ref" : "#/components/schemas/ReplenishmentItem"
                }
              },
              "application/xml" : {
                "schema" : {
                  "$ref" : "#/components/schemas/ReplenishmentItem"
                }
              }
            }
          }
        }
      }
    },
    "/v1.0/warehouses/{warehouseId}/replenishment-items" : {
      "get" : {
        "tags" : [ "ReplenishmentItem" ],
        "operationId" : "getWarehouseIdReplenishmentItemsPage",
        "parameters" : [ {
          "name" : "warehouseId",
          "in" : "path",
          "required" : true,
          "schema" : {
            "type" : "string"
          }
        }, {
          "name" : "page",
          "in" : "query",
          "schema" : {
            "type" : "string"
          }
        }, {
          "name" : "pageSize",
          "in" : "query",
          "schema" : {
            "type" : "string"
          }
        } ],
        "responses" : {
          "default" : {
            "description" : "default response",
            "content" : {
              "application/json" : {
                "schema" : {
                  "$ref" : "#/components/schemas/PageReplenishmentItem"
                }
              },
              "application/xml" : {
                "schema" : {
                  "$ref" : "#/components/schemas/PageReplenishmentItem"
                }
              }
            }
          }
        }
      }
    },
    "/v1.0/skus/by-sku/{sku}/replenishment-items" : {
      "get" : {
        "tags" : [ "ReplenishmentItem" ],
        "operationId" : "getReplenishmentItemsPage",
        "parameters" : [ {
          "name" : "sku",
          "in" : "path",
          "required" : true,
          "schema" : {
            "type" : "string"
          }
        }, {
          "name" : "page",
          "in" : "query",
          "schema" : {
            "type" : "string"
          }
        }, {
          "name" : "pageSize",
          "in" : "query",
          "schema" : {
            "type" : "string"
          }
        } ],
        "responses" : {
          "default" : {
            "description" : "default response",
            "content" : {
              "application/json" : {
                "schema" : {
                  "$ref" : "#/components/schemas/PageReplenishmentItem"
                }
              },
              "application/xml" : {
                "schema" : {
                  "$ref" : "#/components/schemas/PageReplenishmentItem"
                }
              }
            }
          }
        }
      }
    },
    "/v1.0/replenishment-items/by-externalReferenceCode/{externalReferenceCode}" : {
      "get" : {
        "tags" : [ "ReplenishmentItem" ],
        "operationId" : "getReplenishmentItemByExternalReferenceCode",
        "parameters" : [ {
          "name" : "externalReferenceCode",
          "in" : "path",
          "required" : true,
          "schema" : {
            "type" : "string"
          }
        } ],
        "responses" : {
          "default" : {
            "description" : "default response",
            "content" : {
              "application/json" : {
                "schema" : {
                  "$ref" : "#/components/schemas/ReplenishmentItem"
                }
              },
              "application/xml" : {
                "schema" : {
                  "$ref" : "#/components/schemas/ReplenishmentItem"
                }
              }
            }
          }
        }
      },
      "put" : {
        "tags" : [ "ReplenishmentItem" ],
        "operationId" : "putReplenishmentItemByExternalReferenceCode",
        "parameters" : [ {
          "name" : "externalReferenceCode",
          "in" : "path",
          "required" : true,
          "schema" : {
            "type" : "string"
          }
        } ],
        "requestBody" : {
          "content" : {
            "application/json" : {
              "schema" : {
                "$ref" : "#/components/schemas/ReplenishmentItem"
              }
            },
            "application/xml" : {
              "schema" : {
                "$ref" : "#/components/schemas/ReplenishmentItem"
              }
            }
          }
        },
        "responses" : {
          "default" : {
            "description" : "default response",
            "content" : {
              "application/json" : {
                "schema" : {
                  "$ref" : "#/components/schemas/ReplenishmentItem"
                }
              },
              "application/xml" : {
                "schema" : {
                  "$ref" : "#/components/schemas/ReplenishmentItem"
                }
              }
            }
          }
        }
      },
      "delete" : {
        "tags" : [ "ReplenishmentItem" ],
        "operationId" : "deleteReplenishmentItemByExternalReferenceCode",
        "parameters" : [ {
          "name" : "externalReferenceCode",
          "in" : "path",
          "required" : true,
          "schema" : {
            "type" : "string"
          }
        } ],
        "responses" : {
          "default" : {
            "description" : "default response",
            "content" : {
              "application/json" : { },
              "application/xml" : { }
            }
          }
        }
      },
      "patch" : {
        "tags" : [ "ReplenishmentItem" ],
        "operationId" : "patchReplenishmentItemByExternalReferenceCode",
        "parameters" : [ {
          "name" : "externalReferenceCode",
          "in" : "path",
          "required" : true,
          "schema" : {
            "type" : "string"
          }
        } ],
        "requestBody" : {
          "content" : {
            "application/json" : {
              "schema" : {
                "$ref" : "#/components/schemas/ReplenishmentItem"
              }
            },
            "application/xml" : {
              "schema" : {
                "$ref" : "#/components/schemas/ReplenishmentItem"
              }
            }
          }
        },
        "responses" : {
          "default" : {
            "description" : "default response",
            "content" : {
              "application/json" : {
                "schema" : {
                  "$ref" : "#/components/schemas/ReplenishmentItem"
                }
              },
              "application/xml" : {
                "schema" : {
                  "$ref" : "#/components/schemas/ReplenishmentItem"
                }
              }
            }
          }
        }
      }
    },
    "/v1.0/skus/by-sku/{sku}/replenishment-items/export-batch" : {
      "post" : {
        "tags" : [ "ReplenishmentItem" ],
        "operationId" : "postReplenishmentItemsPageExportBatch",
        "parameters" : [ {
          "name" : "sku",
          "in" : "path",
          "required" : true,
          "schema" : {
            "type" : "string"
          }
        }, {
          "name" : "callbackURL",
          "in" : "query",
          "schema" : {
            "type" : "string"
          }
        }, {
          "name" : "contentType",
          "in" : "query",
          "schema" : {
            "type" : "string"
          }
        }, {
          "name" : "fieldNames",
          "in" : "query",
          "schema" : {
            "type" : "string"
          }
        } ],
        "responses" : {
          "default" : {
            "description" : "default response",
            "content" : {
              "application/json" : { }
            }
          }
        }
      }
    },
    "/v1.0/replenishment-items/batch" : {
      "delete" : {
        "tags" : [ "ReplenishmentItem" ],
        "operationId" : "deleteReplenishmentItemBatch",
        "parameters" : [ {
          "name" : "callbackURL",
          "in" : "query",
          "schema" : {
            "type" : "string"
          }
        } ],
        "requestBody" : {
          "content" : {
            "application/json" : {
              "schema" : {
                "type" : "object"
              }
            }
          }
        },
        "responses" : {
          "default" : {
            "description" : "default response",
            "content" : {
              "application/json" : { }
            }
          }
        }
      }
    },
    "/v1.0/warehouses/{warehouseId}/skus/by-sku/{sku}/replenishment-items/batch" : {
      "post" : {
        "tags" : [ "ReplenishmentItem" ],
        "operationId" : "postReplenishmentItemBatch",
        "parameters" : [ {
          "name" : "warehouseId",
          "in" : "path",
          "required" : true,
          "schema" : {
            "type" : "string"
          }
        }, {
          "name" : "sku",
          "in" : "path",
          "required" : true,
          "schema" : {
            "type" : "string"
          }
        }, {
          "name" : "callbackURL",
          "in" : "query",
          "schema" : {
            "type" : "string"
          }
        } ],
        "requestBody" : {
          "content" : {
            "application/json" : {
              "schema" : {
                "type" : "object"
              }
            }
          }
        },
        "responses" : {
          "default" : {
            "description" : "default response",
            "content" : {
              "application/json" : { }
            }
          }
        }
      }
    },
    "/v1.0/warehouses/{id}/warehouse-account-groups" : {
      "get" : {
        "tags" : [ "WarehouseAccountGroup" ],
        "operationId" : "getWarehouseIdWarehouseAccountGroupsPage",
        "parameters" : [ {
          "name" : "id",
          "in" : "path",
          "required" : true,
          "schema" : {
            "type" : "string"
          }
        }, {
          "name" : "filter",
          "in" : "query",
          "schema" : {
            "type" : "string"
          }
        }, {
          "name" : "page",
          "in" : "query",
          "schema" : {
            "type" : "string"
          }
        }, {
          "name" : "pageSize",
          "in" : "query",
          "schema" : {
            "type" : "string"
          }
        }, {
          "name" : "search",
          "in" : "query",
          "schema" : {
            "type" : "string"
          }
        }, {
          "name" : "sort",
          "in" : "query",
          "schema" : {
            "type" : "string"
          }
        } ],
        "responses" : {
          "default" : {
            "description" : "default response",
            "content" : {
              "application/json" : {
                "schema" : {
                  "$ref" : "#/components/schemas/PageWarehouseAccountGroup"
                }
              },
              "application/xml" : {
                "schema" : {
                  "$ref" : "#/components/schemas/PageWarehouseAccountGroup"
                }
              }
            }
          }
        }
      },
      "post" : {
        "tags" : [ "WarehouseAccountGroup" ],
        "operationId" : "postWarehouseIdWarehouseAccountGroup",
        "parameters" : [ {
          "name" : "id",
          "in" : "path",
          "required" : true,
          "schema" : {
            "type" : "string"
          }
        } ],
        "requestBody" : {
          "content" : {
            "application/json" : {
              "schema" : {
                "$ref" : "#/components/schemas/WarehouseAccountGroup"
              }
            },
            "application/xml" : {
              "schema" : {
                "$ref" : "#/components/schemas/WarehouseAccountGroup"
              }
            }
          }
        },
        "responses" : {
          "default" : {
            "description" : "default response",
            "content" : {
              "application/json" : {
                "schema" : {
                  "$ref" : "#/components/schemas/WarehouseAccountGroup"
                }
              },
              "application/xml" : {
                "schema" : {
                  "$ref" : "#/components/schemas/WarehouseAccountGroup"
                }
              }
            }
          }
        }
      }
    },
    "/v1.0/warehouse-account-groups/{warehouseAccountGroupId}" : {
      "delete" : {
        "tags" : [ "WarehouseAccountGroup" ],
        "operationId" : "deleteWarehouseAccountGroup",
        "parameters" : [ {
          "name" : "warehouseAccountGroupId",
          "in" : "path",
          "required" : true,
          "schema" : {
            "type" : "string"
          }
        } ],
        "responses" : {
          "default" : {
            "description" : "default response",
            "content" : {
              "application/json" : { },
              "application/xml" : { }
            }
          }
        }
      }
    },
    "/v1.0/warehouses/by-externalReferenceCode/{externalReferenceCode}/warehouse-account-groups" : {
      "get" : {
        "tags" : [ "WarehouseAccountGroup" ],
        "operationId" : "getWarehouseByExternalReferenceCodeWarehouseAccountGroupsPage",
        "parameters" : [ {
          "name" : "externalReferenceCode",
          "in" : "path",
          "required" : true,
          "schema" : {
            "type" : "string"
          }
        }, {
          "name" : "page",
          "in" : "query",
          "schema" : {
            "type" : "string"
          }
        }, {
          "name" : "pageSize",
          "in" : "query",
          "schema" : {
            "type" : "string"
          }
        } ],
        "responses" : {
          "default" : {
            "description" : "default response",
            "content" : {
              "application/json" : {
                "schema" : {
                  "$ref" : "#/components/schemas/PageWarehouseAccountGroup"
                }
              },
              "application/xml" : {
                "schema" : {
                  "$ref" : "#/components/schemas/PageWarehouseAccountGroup"
                }
              }
            }
          }
        }
      },
      "post" : {
        "tags" : [ "WarehouseAccountGroup" ],
        "operationId" : "postWarehouseByExternalReferenceCodeWarehouseAccountGroup",
        "parameters" : [ {
          "name" : "externalReferenceCode",
          "in" : "path",
          "required" : true,
          "schema" : {
            "type" : "string"
          }
        } ],
        "requestBody" : {
          "content" : {
            "application/json" : {
              "schema" : {
                "$ref" : "#/components/schemas/WarehouseAccountGroup"
              }
            },
            "application/xml" : {
              "schema" : {
                "$ref" : "#/components/schemas/WarehouseAccountGroup"
              }
            }
          }
        },
        "responses" : {
          "default" : {
            "description" : "default response",
            "content" : {
              "application/json" : {
                "schema" : {
                  "$ref" : "#/components/schemas/WarehouseAccountGroup"
                }
              },
              "application/xml" : {
                "schema" : {
                  "$ref" : "#/components/schemas/WarehouseAccountGroup"
                }
              }
            }
          }
        }
      }
    },
    "/v1.0/warehouse-account-groups/batch" : {
      "delete" : {
        "tags" : [ "WarehouseAccountGroup" ],
        "operationId" : "deleteWarehouseAccountGroupBatch",
        "parameters" : [ {
          "name" : "callbackURL",
          "in" : "query",
          "schema" : {
            "type" : "string"
          }
        } ],
        "requestBody" : {
          "content" : {
            "application/json" : {
              "schema" : {
                "type" : "object"
              }
            }
          }
        },
        "responses" : {
          "default" : {
            "description" : "default response",
            "content" : {
              "application/json" : { }
            }
          }
        }
      }
    },
    "/v1.0/warehouses/warehouse-account-groups/batch" : {
      "post" : {
        "tags" : [ "WarehouseAccountGroup" ],
        "operationId" : "postWarehouseIdWarehouseAccountGroupBatch",
        "parameters" : [ {
          "name" : "callbackURL",
          "in" : "query",
          "schema" : {
            "type" : "string"
          }
        } ],
        "requestBody" : {
          "content" : {
            "application/json" : {
              "schema" : {
                "type" : "object"
              }
            }
          }
        },
        "responses" : {
          "default" : {
            "description" : "default response",
            "content" : {
              "application/json" : { }
            }
          }
        }
      }
    },
    "/v1.0/warehouse-accounts/{warehouseAccountId}" : {
      "delete" : {
        "tags" : [ "WarehouseAccount" ],
        "operationId" : "deleteWarehouseAccount",
        "parameters" : [ {
          "name" : "warehouseAccountId",
          "in" : "path",
          "required" : true,
          "schema" : {
            "type" : "string"
          }
        } ],
        "responses" : {
          "default" : {
            "description" : "default response",
            "content" : {
              "application/json" : { },
              "application/xml" : { }
            }
          }
        }
      }
    },
    "/v1.0/warehouses/by-externalReferenceCode/{externalReferenceCode}/warehouse-accounts" : {
      "get" : {
        "tags" : [ "WarehouseAccount" ],
        "operationId" : "getWarehouseByExternalReferenceCodeWarehouseAccountsPage",
        "parameters" : [ {
          "name" : "externalReferenceCode",
          "in" : "path",
          "required" : true,
          "schema" : {
            "type" : "string"
          }
        }, {
          "name" : "page",
          "in" : "query",
          "schema" : {
            "type" : "string"
          }
        }, {
          "name" : "pageSize",
          "in" : "query",
          "schema" : {
            "type" : "string"
          }
        } ],
        "responses" : {
          "default" : {
            "description" : "default response",
            "content" : {
              "application/json" : {
                "schema" : {
                  "$ref" : "#/components/schemas/PageWarehouseAccount"
                }
              },
              "application/xml" : {
                "schema" : {
                  "$ref" : "#/components/schemas/PageWarehouseAccount"
                }
              }
            }
          }
        }
      },
      "post" : {
        "tags" : [ "WarehouseAccount" ],
        "operationId" : "postWarehouseByExternalReferenceCodeWarehouseAccount",
        "parameters" : [ {
          "name" : "externalReferenceCode",
          "in" : "path",
          "required" : true,
          "schema" : {
            "type" : "string"
          }
        } ],
        "requestBody" : {
          "content" : {
            "application/json" : {
              "schema" : {
                "$ref" : "#/components/schemas/WarehouseAccount"
              }
            },
            "application/xml" : {
              "schema" : {
                "$ref" : "#/components/schemas/WarehouseAccount"
              }
            }
          }
        },
        "responses" : {
          "default" : {
            "description" : "default response",
            "content" : {
              "application/json" : {
                "schema" : {
                  "$ref" : "#/components/schemas/WarehouseAccount"
                }
              },
              "application/xml" : {
                "schema" : {
                  "$ref" : "#/components/schemas/WarehouseAccount"
                }
              }
            }
          }
        }
      }
    },
    "/v1.0/warehouses/{id}/warehouse-accounts" : {
      "get" : {
        "tags" : [ "WarehouseAccount" ],
        "operationId" : "getWarehouseIdWarehouseAccountsPage",
        "parameters" : [ {
          "name" : "id",
          "in" : "path",
          "required" : true,
          "schema" : {
            "type" : "string"
          }
        }, {
          "name" : "filter",
          "in" : "query",
          "schema" : {
            "type" : "string"
          }
        }, {
          "name" : "page",
          "in" : "query",
          "schema" : {
            "type" : "string"
          }
        }, {
          "name" : "pageSize",
          "in" : "query",
          "schema" : {
            "type" : "string"
          }
        }, {
          "name" : "search",
          "in" : "query",
          "schema" : {
            "type" : "string"
          }
        }, {
          "name" : "sort",
          "in" : "query",
          "schema" : {
            "type" : "string"
          }
        } ],
        "responses" : {
          "default" : {
            "description" : "default response",
            "content" : {
              "application/json" : {
                "schema" : {
                  "$ref" : "#/components/schemas/PageWarehouseAccount"
                }
              },
              "application/xml" : {
                "schema" : {
                  "$ref" : "#/components/schemas/PageWarehouseAccount"
                }
              }
            }
          }
        }
      },
      "post" : {
        "tags" : [ "WarehouseAccount" ],
        "operationId" : "postWarehouseIdWarehouseAccount",
        "parameters" : [ {
          "name" : "id",
          "in" : "path",
          "required" : true,
          "schema" : {
            "type" : "string"
          }
        } ],
        "requestBody" : {
          "content" : {
            "application/json" : {
              "schema" : {
                "$ref" : "#/components/schemas/WarehouseAccount"
              }
            },
            "application/xml" : {
              "schema" : {
                "$ref" : "#/components/schemas/WarehouseAccount"
              }
            }
          }
        },
        "responses" : {
          "default" : {
            "description" : "default response",
            "content" : {
              "application/json" : {
                "schema" : {
                  "$ref" : "#/components/schemas/WarehouseAccount"
                }
              },
              "application/xml" : {
                "schema" : {
                  "$ref" : "#/components/schemas/WarehouseAccount"
                }
              }
            }
          }
        }
      }
    },
    "/v1.0/warehouses/warehouse-accounts/batch" : {
      "post" : {
        "tags" : [ "WarehouseAccount" ],
        "operationId" : "postWarehouseIdWarehouseAccountBatch",
        "parameters" : [ {
          "name" : "callbackURL",
          "in" : "query",
          "schema" : {
            "type" : "string"
          }
        } ],
        "requestBody" : {
          "content" : {
            "application/json" : {
              "schema" : {
                "type" : "object"
              }
            }
          }
        },
        "responses" : {
          "default" : {
            "description" : "default response",
            "content" : {
              "application/json" : { }
            }
          }
        }
      }
    },
    "/v1.0/warehouse-accounts/batch" : {
      "delete" : {
        "tags" : [ "WarehouseAccount" ],
        "operationId" : "deleteWarehouseAccountBatch",
        "parameters" : [ {
          "name" : "callbackURL",
          "in" : "query",
          "schema" : {
            "type" : "string"
          }
        } ],
        "requestBody" : {
          "content" : {
            "application/json" : {
              "schema" : {
                "type" : "object"
              }
            }
          }
        },
        "responses" : {
          "default" : {
            "description" : "default response",
            "content" : {
              "application/json" : { }
            }
          }
        }
      }
    },
    "/v1.0/warehouse-channels/{warehouseChannelId}" : {
      "delete" : {
        "tags" : [ "WarehouseChannel" ],
        "operationId" : "deleteWarehouseChannel",
        "parameters" : [ {
          "name" : "warehouseChannelId",
          "in" : "path",
          "required" : true,
          "schema" : {
            "type" : "string"
          }
        } ],
        "responses" : {
          "default" : {
            "description" : "default response",
            "content" : {
              "application/json" : { },
              "application/xml" : { }
            }
          }
        }
      }
    },
    "/v1.0/warehouses/by-externalReferenceCode/{externalReferenceCode}/warehouse-channels" : {
      "get" : {
        "tags" : [ "WarehouseChannel" ],
        "operationId" : "getWarehouseByExternalReferenceCodeWarehouseChannelsPage",
        "parameters" : [ {
          "name" : "externalReferenceCode",
          "in" : "path",
          "required" : true,
          "schema" : {
            "type" : "string"
          }
        }, {
          "name" : "page",
          "in" : "query",
          "schema" : {
            "type" : "string"
          }
        }, {
          "name" : "pageSize",
          "in" : "query",
          "schema" : {
            "type" : "string"
          }
        } ],
        "responses" : {
          "default" : {
            "description" : "default response",
            "content" : {
              "application/json" : {
                "schema" : {
                  "$ref" : "#/components/schemas/PageWarehouseChannel"
                }
              },
              "application/xml" : {
                "schema" : {
                  "$ref" : "#/components/schemas/PageWarehouseChannel"
                }
              }
            }
          }
        }
      },
      "post" : {
        "tags" : [ "WarehouseChannel" ],
        "operationId" : "postWarehouseByExternalReferenceCodeWarehouseChannel",
        "parameters" : [ {
          "name" : "externalReferenceCode",
          "in" : "path",
          "required" : true,
          "schema" : {
            "type" : "string"
          }
        } ],
        "requestBody" : {
          "content" : {
            "application/json" : {
              "schema" : {
                "$ref" : "#/components/schemas/WarehouseChannel"
              }
            },
            "application/xml" : {
              "schema" : {
                "$ref" : "#/components/schemas/WarehouseChannel"
              }
            }
          }
        },
        "responses" : {
          "default" : {
            "description" : "default response",
            "content" : {
              "application/json" : {
                "schema" : {
                  "$ref" : "#/components/schemas/WarehouseChannel"
                }
              },
              "application/xml" : {
                "schema" : {
                  "$ref" : "#/components/schemas/WarehouseChannel"
                }
              }
            }
          }
        }
      }
    },
    "/v1.0/warehouses/{id}/warehouse-channels" : {
      "get" : {
        "tags" : [ "WarehouseChannel" ],
        "operationId" : "getWarehouseIdWarehouseChannelsPage",
        "parameters" : [ {
          "name" : "id",
          "in" : "path",
          "required" : true,
          "schema" : {
            "type" : "string"
          }
        }, {
          "name" : "filter",
          "in" : "query",
          "schema" : {
            "type" : "string"
          }
        }, {
          "name" : "page",
          "in" : "query",
          "schema" : {
            "type" : "string"
          }
        }, {
          "name" : "pageSize",
          "in" : "query",
          "schema" : {
            "type" : "string"
          }
        }, {
          "name" : "search",
          "in" : "query",
          "schema" : {
            "type" : "string"
          }
        }, {
          "name" : "sort",
          "in" : "query",
          "schema" : {
            "type" : "string"
          }
        } ],
        "responses" : {
          "default" : {
            "description" : "default response",
            "content" : {
              "application/json" : {
                "schema" : {
                  "$ref" : "#/components/schemas/PageWarehouseChannel"
                }
              },
              "application/xml" : {
                "schema" : {
                  "$ref" : "#/components/schemas/PageWarehouseChannel"
                }
              }
            }
          }
        }
      },
      "post" : {
        "tags" : [ "WarehouseChannel" ],
        "operationId" : "postWarehouseIdWarehouseChannel",
        "parameters" : [ {
          "name" : "id",
          "in" : "path",
          "required" : true,
          "schema" : {
            "type" : "string"
          }
        } ],
        "requestBody" : {
          "content" : {
            "application/json" : {
              "schema" : {
                "$ref" : "#/components/schemas/WarehouseChannel"
              }
            },
            "application/xml" : {
              "schema" : {
                "$ref" : "#/components/schemas/WarehouseChannel"
              }
            }
          }
        },
        "responses" : {
          "default" : {
            "description" : "default response",
            "content" : {
              "application/json" : {
                "schema" : {
                  "$ref" : "#/components/schemas/WarehouseChannel"
                }
              },
              "application/xml" : {
                "schema" : {
                  "$ref" : "#/components/schemas/WarehouseChannel"
                }
              }
            }
          }
        }
      }
    },
    "/v1.0/warehouses/warehouse-channels/batch" : {
      "post" : {
        "tags" : [ "WarehouseChannel" ],
        "operationId" : "postWarehouseIdWarehouseChannelBatch",
        "parameters" : [ {
          "name" : "callbackURL",
          "in" : "query",
          "schema" : {
            "type" : "string"
          }
        } ],
        "requestBody" : {
          "content" : {
            "application/json" : {
              "schema" : {
                "type" : "object"
              }
            }
          }
        },
        "responses" : {
          "default" : {
            "description" : "default response",
            "content" : {
              "application/json" : { }
            }
          }
        }
      }
    },
    "/v1.0/warehouse-channels/batch" : {
      "delete" : {
        "tags" : [ "WarehouseChannel" ],
        "operationId" : "deleteWarehouseChannelBatch",
        "parameters" : [ {
          "name" : "callbackURL",
          "in" : "query",
          "schema" : {
            "type" : "string"
          }
        } ],
        "requestBody" : {
          "content" : {
            "application/json" : {
              "schema" : {
                "type" : "object"
              }
            }
          }
        },
        "responses" : {
          "default" : {
            "description" : "default response",
            "content" : {
              "application/json" : { }
            }
          }
        }
      }
    },
    "/v1.0/warehouseItems/{id}" : {
      "get" : {
        "tags" : [ "WarehouseItem" ],
        "operationId" : "getWarehouseItem",
        "parameters" : [ {
          "name" : "id",
          "in" : "path",
          "required" : true,
          "schema" : {
            "type" : "string"
          }
        } ],
        "responses" : {
          "default" : {
            "description" : "default response",
            "content" : {
              "application/json" : {
                "schema" : {
                  "$ref" : "#/components/schemas/WarehouseItem"
                }
              },
              "application/xml" : {
                "schema" : {
                  "$ref" : "#/components/schemas/WarehouseItem"
                }
              }
            }
          }
        }
      },
      "delete" : {
        "tags" : [ "WarehouseItem" ],
        "operationId" : "deleteWarehouseItem",
        "parameters" : [ {
          "name" : "id",
          "in" : "path",
          "required" : true,
          "schema" : {
            "type" : "string"
          }
        } ],
        "responses" : {
          "default" : {
            "description" : "default response",
            "content" : {
              "application/json" : { },
              "application/xml" : { }
            }
          }
        }
      },
      "patch" : {
        "tags" : [ "WarehouseItem" ],
        "operationId" : "patchWarehouseItem",
        "parameters" : [ {
          "name" : "id",
          "in" : "path",
          "required" : true,
          "schema" : {
            "type" : "string"
          }
        } ],
        "requestBody" : {
          "content" : {
            "application/json" : {
              "schema" : {
                "$ref" : "#/components/schemas/WarehouseItem"
              }
            },
            "application/xml" : {
              "schema" : {
                "$ref" : "#/components/schemas/WarehouseItem"
              }
            }
          }
        },
        "responses" : {
          "default" : {
            "description" : "default response",
            "content" : {
              "application/json" : { },
              "application/xml" : { }
            }
          }
        }
      }
    },
    "/v1.0/warehouses/by-externalReferenceCode/{externalReferenceCode}/warehouseItems" : {
      "get" : {
        "tags" : [ "WarehouseItem" ],
        "operationId" : "getWarehouseByExternalReferenceCodeWarehouseItemsPage",
        "parameters" : [ {
          "name" : "externalReferenceCode",
          "in" : "path",
          "required" : true,
          "schema" : {
            "type" : "string"
          }
        }, {
          "name" : "page",
          "in" : "query",
          "schema" : {
            "type" : "string"
          }
        }, {
          "name" : "pageSize",
          "in" : "query",
          "schema" : {
            "type" : "string"
          }
        } ],
        "responses" : {
          "default" : {
            "description" : "default response",
            "content" : {
              "application/json" : {
                "schema" : {
                  "$ref" : "#/components/schemas/PageWarehouseItem"
                }
              },
              "application/xml" : {
                "schema" : {
                  "$ref" : "#/components/schemas/PageWarehouseItem"
                }
              }
            }
          }
        }
      },
      "post" : {
        "tags" : [ "WarehouseItem" ],
        "operationId" : "postWarehouseByExternalReferenceCodeWarehouseItem",
        "parameters" : [ {
          "name" : "externalReferenceCode",
          "in" : "path",
          "required" : true,
          "schema" : {
            "type" : "string"
          }
        } ],
        "requestBody" : {
          "content" : {
            "application/json" : {
              "schema" : {
                "$ref" : "#/components/schemas/WarehouseItem"
              }
            },
            "application/xml" : {
              "schema" : {
                "$ref" : "#/components/schemas/WarehouseItem"
              }
            }
          }
        },
        "responses" : {
          "default" : {
            "description" : "default response",
            "content" : {
              "application/json" : {
                "schema" : {
                  "$ref" : "#/components/schemas/WarehouseItem"
                }
              },
              "application/xml" : {
                "schema" : {
                  "$ref" : "#/components/schemas/WarehouseItem"
                }
              }
            }
          }
        }
      }
    },
    "/v1.0/warehouses/{id}/warehouseItems" : {
      "get" : {
        "tags" : [ "WarehouseItem" ],
        "operationId" : "getWarehouseIdWarehouseItemsPage",
        "parameters" : [ {
          "name" : "id",
          "in" : "path",
          "required" : true,
          "schema" : {
            "type" : "string"
          }
        }, {
          "name" : "page",
          "in" : "query",
          "schema" : {
            "type" : "string"
          }
        }, {
          "name" : "pageSize",
          "in" : "query",
          "schema" : {
            "type" : "string"
          }
        } ],
        "responses" : {
          "default" : {
            "description" : "default response",
            "content" : {
              "application/json" : {
                "schema" : {
                  "$ref" : "#/components/schemas/PageWarehouseItem"
                }
              },
              "application/xml" : {
                "schema" : {
                  "$ref" : "#/components/schemas/PageWarehouseItem"
                }
              }
            }
          }
        }
      },
      "post" : {
        "tags" : [ "WarehouseItem" ],
        "operationId" : "postWarehouseIdWarehouseItem",
        "parameters" : [ {
          "name" : "id",
          "in" : "path",
          "required" : true,
          "schema" : {
            "type" : "string"
          }
        } ],
        "requestBody" : {
          "content" : {
            "application/json" : {
              "schema" : {
                "$ref" : "#/components/schemas/WarehouseItem"
              }
            },
            "application/xml" : {
              "schema" : {
                "$ref" : "#/components/schemas/WarehouseItem"
              }
            }
          }
        },
        "responses" : {
          "default" : {
            "description" : "default response",
            "content" : {
              "application/json" : {
                "schema" : {
                  "$ref" : "#/components/schemas/WarehouseItem"
                }
              },
              "application/xml" : {
                "schema" : {
                  "$ref" : "#/components/schemas/WarehouseItem"
                }
              }
            }
          }
        }
      }
    },
    "/v1.0/warehouseItems/updated" : {
      "get" : {
        "tags" : [ "WarehouseItem" ],
        "operationId" : "getWarehouseItemsUpdatedPage",
        "parameters" : [ {
          "name" : "end",
          "in" : "query",
          "schema" : {
            "type" : "string"
          }
        }, {
          "name" : "page",
          "in" : "query",
          "schema" : {
            "type" : "string"
          }
        }, {
          "name" : "pageSize",
          "in" : "query",
          "schema" : {
            "type" : "string"
          }
        }, {
          "name" : "start",
          "in" : "query",
          "schema" : {
            "type" : "string"
          }
        } ],
        "responses" : {
          "default" : {
            "description" : "default response",
            "content" : {
              "application/json" : {
                "schema" : {
                  "$ref" : "#/components/schemas/PageWarehouseItem"
                }
              },
              "application/xml" : {
                "schema" : {
                  "$ref" : "#/components/schemas/PageWarehouseItem"
                }
              }
            }
          }
        }
      }
    },
    "/v1.0/warehouseItems/by-externalReferenceCode/{externalReferenceCode}" : {
      "get" : {
        "tags" : [ "WarehouseItem" ],
        "operationId" : "getWarehouseItemByExternalReferenceCode",
        "parameters" : [ {
          "name" : "externalReferenceCode",
          "in" : "path",
          "required" : true,
          "schema" : {
            "type" : "string"
          }
        } ],
        "responses" : {
          "default" : {
            "description" : "default response",
            "content" : {
              "application/json" : {
                "schema" : {
                  "$ref" : "#/components/schemas/WarehouseItem"
                }
              },
              "application/xml" : {
                "schema" : {
                  "$ref" : "#/components/schemas/WarehouseItem"
                }
              }
            }
          }
        }
      },
      "post" : {
        "tags" : [ "WarehouseItem" ],
        "operationId" : "postWarehouseItemByExternalReferenceCode",
        "parameters" : [ {
          "name" : "externalReferenceCode",
          "in" : "path",
          "required" : true,
          "schema" : {
            "type" : "string"
          }
        } ],
        "requestBody" : {
          "content" : {
            "application/json" : {
              "schema" : {
                "$ref" : "#/components/schemas/WarehouseItem"
              }
            },
            "application/xml" : {
              "schema" : {
                "$ref" : "#/components/schemas/WarehouseItem"
              }
            }
          }
        },
        "responses" : {
          "default" : {
            "description" : "default response",
            "content" : {
              "application/json" : {
                "schema" : {
                  "$ref" : "#/components/schemas/WarehouseItem"
                }
              },
              "application/xml" : {
                "schema" : {
                  "$ref" : "#/components/schemas/WarehouseItem"
                }
              }
            }
          }
        }
      },
      "delete" : {
        "tags" : [ "WarehouseItem" ],
        "operationId" : "deleteWarehouseItemByExternalReferenceCode",
        "parameters" : [ {
          "name" : "externalReferenceCode",
          "in" : "path",
          "required" : true,
          "schema" : {
            "type" : "string"
          }
        } ],
        "responses" : {
          "default" : {
            "description" : "default response",
            "content" : {
              "application/json" : { },
              "application/xml" : { }
            }
          }
        }
      },
      "patch" : {
        "tags" : [ "WarehouseItem" ],
        "operationId" : "patchWarehouseItemByExternalReferenceCode",
        "parameters" : [ {
          "name" : "externalReferenceCode",
          "in" : "path",
          "required" : true,
          "schema" : {
            "type" : "string"
          }
        } ],
        "requestBody" : {
          "content" : {
            "application/json" : {
              "schema" : {
                "$ref" : "#/components/schemas/WarehouseItem"
              }
            },
            "application/xml" : {
              "schema" : {
                "$ref" : "#/components/schemas/WarehouseItem"
              }
            }
          }
        },
        "responses" : {
          "default" : {
            "description" : "default response",
            "content" : {
              "application/json" : { },
              "application/xml" : { }
            }
          }
        }
      }
    },
    "/v1.0/warehouses/warehouseItems/batch" : {
      "post" : {
        "tags" : [ "WarehouseItem" ],
        "operationId" : "postWarehouseIdWarehouseItemBatch",
        "parameters" : [ {
          "name" : "callbackURL",
          "in" : "query",
          "schema" : {
            "type" : "string"
          }
        } ],
        "requestBody" : {
          "content" : {
            "application/json" : {
              "schema" : {
                "type" : "object"
              }
            }
          }
        },
        "responses" : {
          "default" : {
            "description" : "default response",
            "content" : {
              "application/json" : { }
            }
          }
        }
      }
    },
    "/v1.0/warehouseItems/batch" : {
      "delete" : {
        "tags" : [ "WarehouseItem" ],
        "operationId" : "deleteWarehouseItemBatch",
        "parameters" : [ {
          "name" : "callbackURL",
          "in" : "query",
          "schema" : {
            "type" : "string"
          }
        } ],
        "requestBody" : {
          "content" : {
            "application/json" : {
              "schema" : {
                "type" : "object"
              }
            }
          }
        },
        "responses" : {
          "default" : {
            "description" : "default response",
            "content" : {
              "application/json" : { }
            }
          }
        }
      }
    },
    "/v1.0/warehouses/by-externalReferenceCode/{externalReferenceCode}/warehouse-order-types" : {
      "get" : {
        "tags" : [ "WarehouseOrderType" ],
        "operationId" : "getWarehouseByExternalReferenceCodeWarehouseOrderTypesPage",
        "parameters" : [ {
          "name" : "externalReferenceCode",
          "in" : "path",
          "required" : true,
          "schema" : {
            "type" : "string"
          }
        }, {
          "name" : "page",
          "in" : "query",
          "schema" : {
            "type" : "string"
          }
        }, {
          "name" : "pageSize",
          "in" : "query",
          "schema" : {
            "type" : "string"
          }
        } ],
        "responses" : {
          "default" : {
            "description" : "default response",
            "content" : {
              "application/json" : {
                "schema" : {
                  "$ref" : "#/components/schemas/PageWarehouseOrderType"
                }
              },
              "application/xml" : {
                "schema" : {
                  "$ref" : "#/components/schemas/PageWarehouseOrderType"
                }
              }
            }
          }
        }
      },
      "post" : {
        "tags" : [ "WarehouseOrderType" ],
        "operationId" : "postWarehouseByExternalReferenceCodeWarehouseOrderType",
        "parameters" : [ {
          "name" : "externalReferenceCode",
          "in" : "path",
          "required" : true,
          "schema" : {
            "type" : "string"
          }
        } ],
        "requestBody" : {
          "content" : {
            "application/json" : {
              "schema" : {
                "$ref" : "#/components/schemas/WarehouseOrderType"
              }
            },
            "application/xml" : {
              "schema" : {
                "$ref" : "#/components/schemas/WarehouseOrderType"
              }
            }
          }
        },
        "responses" : {
          "default" : {
            "description" : "default response",
            "content" : {
              "application/json" : {
                "schema" : {
                  "$ref" : "#/components/schemas/WarehouseOrderType"
                }
              },
              "application/xml" : {
                "schema" : {
                  "$ref" : "#/components/schemas/WarehouseOrderType"
                }
              }
            }
          }
        }
      }
    },
    "/v1.0/warehouses/{id}/warehouse-order-types" : {
      "get" : {
        "tags" : [ "WarehouseOrderType" ],
        "operationId" : "getWarehouseIdWarehouseOrderTypesPage",
        "parameters" : [ {
          "name" : "id",
          "in" : "path",
          "required" : true,
          "schema" : {
            "type" : "string"
          }
        }, {
          "name" : "filter",
          "in" : "query",
          "schema" : {
            "type" : "string"
          }
        }, {
          "name" : "page",
          "in" : "query",
          "schema" : {
            "type" : "string"
          }
        }, {
          "name" : "pageSize",
          "in" : "query",
          "schema" : {
            "type" : "string"
          }
        }, {
          "name" : "search",
          "in" : "query",
          "schema" : {
            "type" : "string"
          }
        }, {
          "name" : "sort",
          "in" : "query",
          "schema" : {
            "type" : "string"
          }
        } ],
        "responses" : {
          "default" : {
            "description" : "default response",
            "content" : {
              "application/json" : {
                "schema" : {
                  "$ref" : "#/components/schemas/PageWarehouseOrderType"
                }
              },
              "application/xml" : {
                "schema" : {
                  "$ref" : "#/components/schemas/PageWarehouseOrderType"
                }
              }
            }
          }
        }
      },
      "post" : {
        "tags" : [ "WarehouseOrderType" ],
        "operationId" : "postWarehouseIdWarehouseOrderType",
        "parameters" : [ {
          "name" : "id",
          "in" : "path",
          "required" : true,
          "schema" : {
            "type" : "string"
          }
        } ],
        "requestBody" : {
          "content" : {
            "application/json" : {
              "schema" : {
                "$ref" : "#/components/schemas/WarehouseOrderType"
              }
            },
            "application/xml" : {
              "schema" : {
                "$ref" : "#/components/schemas/WarehouseOrderType"
              }
            }
          }
        },
        "responses" : {
          "default" : {
            "description" : "default response",
            "content" : {
              "application/json" : {
                "schema" : {
                  "$ref" : "#/components/schemas/WarehouseOrderType"
                }
              },
              "application/xml" : {
                "schema" : {
                  "$ref" : "#/components/schemas/WarehouseOrderType"
                }
              }
            }
          }
        }
      }
    },
    "/v1.0/warehouse-order-types/{warehouseOrderTypeId}" : {
      "delete" : {
        "tags" : [ "WarehouseOrderType" ],
        "operationId" : "deleteWarehouseOrderType",
        "parameters" : [ {
          "name" : "warehouseOrderTypeId",
          "in" : "path",
          "required" : true,
          "schema" : {
            "type" : "string"
          }
        } ],
        "responses" : {
          "default" : {
            "description" : "default response",
            "content" : {
              "application/json" : { },
              "application/xml" : { }
            }
          }
        }
      }
    },
    "/v1.0/warehouses/warehouse-order-types/batch" : {
      "post" : {
        "tags" : [ "WarehouseOrderType" ],
        "operationId" : "postWarehouseIdWarehouseOrderTypeBatch",
        "parameters" : [ {
          "name" : "callbackURL",
          "in" : "query",
          "schema" : {
            "type" : "string"
          }
        } ],
        "requestBody" : {
          "content" : {
            "application/json" : {
              "schema" : {
                "type" : "object"
              }
            }
          }
        },
        "responses" : {
          "default" : {
            "description" : "default response",
            "content" : {
              "application/json" : { }
            }
          }
        }
      }
    },
    "/v1.0/warehouse-order-types/batch" : {
      "delete" : {
        "tags" : [ "WarehouseOrderType" ],
        "operationId" : "deleteWarehouseOrderTypeBatch",
        "parameters" : [ {
          "name" : "callbackURL",
          "in" : "query",
          "schema" : {
            "type" : "string"
          }
        } ],
        "requestBody" : {
          "content" : {
            "application/json" : {
              "schema" : {
                "type" : "object"
              }
            }
          }
        },
        "responses" : {
          "default" : {
            "description" : "default response",
            "content" : {
              "application/json" : { }
            }
          }
        }
      }
    },
    "/v1.0/warehouses/{id}" : {
      "get" : {
        "tags" : [ "Warehouse" ],
        "operationId" : "getWarehouseId",
        "parameters" : [ {
          "name" : "id",
          "in" : "path",
          "required" : true,
          "schema" : {
            "type" : "string"
          }
        } ],
        "responses" : {
          "default" : {
            "description" : "default response",
            "content" : {
              "application/json" : {
                "schema" : {
                  "$ref" : "#/components/schemas/Warehouse"
                }
              },
              "application/xml" : {
                "schema" : {
                  "$ref" : "#/components/schemas/Warehouse"
                }
              }
            }
          }
        }
      },
      "delete" : {
        "tags" : [ "Warehouse" ],
        "operationId" : "deleteWarehouseId",
        "parameters" : [ {
          "name" : "id",
          "in" : "path",
          "required" : true,
          "schema" : {
            "type" : "string"
          }
        } ],
        "responses" : {
          "default" : {
            "description" : "default response",
            "content" : {
              "application/json" : { },
              "application/xml" : { }
            }
          }
        }
      },
      "patch" : {
        "tags" : [ "Warehouse" ],
        "operationId" : "patchWarehouseId",
        "parameters" : [ {
          "name" : "id",
          "in" : "path",
          "required" : true,
          "schema" : {
            "type" : "string"
          }
        } ],
        "requestBody" : {
          "content" : {
            "application/json" : {
              "schema" : {
                "$ref" : "#/components/schemas/Warehouse"
              }
            },
            "application/xml" : {
              "schema" : {
                "$ref" : "#/components/schemas/Warehouse"
              }
            }
          }
        },
        "responses" : {
          "default" : {
            "description" : "default response",
            "content" : {
              "application/json" : { },
              "application/xml" : { }
            }
          }
        }
      }
    },
    "/v1.0/warehouses" : {
      "get" : {
        "tags" : [ "Warehouse" ],
        "operationId" : "getWarehousesPage",
        "parameters" : [ {
          "name" : "filter",
          "in" : "query",
          "schema" : {
            "type" : "string"
          }
        }, {
          "name" : "page",
          "in" : "query",
          "schema" : {
            "type" : "string"
          }
        }, {
          "name" : "pageSize",
          "in" : "query",
          "schema" : {
            "type" : "string"
          }
        }, {
          "name" : "search",
          "in" : "query",
          "schema" : {
            "type" : "string"
          }
        }, {
          "name" : "sort",
          "in" : "query",
          "schema" : {
            "type" : "string"
          }
        } ],
        "responses" : {
          "default" : {
            "description" : "default response",
            "content" : {
              "application/json" : {
                "schema" : {
                  "$ref" : "#/components/schemas/PageWarehouse"
                }
              },
              "application/xml" : {
                "schema" : {
                  "$ref" : "#/components/schemas/PageWarehouse"
                }
              }
            }
          }
        }
      },
      "post" : {
        "tags" : [ "Warehouse" ],
        "operationId" : "postWarehouse",
        "requestBody" : {
          "content" : {
            "application/json" : {
              "schema" : {
                "$ref" : "#/components/schemas/Warehouse"
              }
            },
            "application/xml" : {
              "schema" : {
                "$ref" : "#/components/schemas/Warehouse"
              }
            }
          }
        },
        "responses" : {
          "default" : {
            "description" : "default response",
            "content" : {
              "application/json" : {
                "schema" : {
                  "$ref" : "#/components/schemas/Warehouse"
                }
              },
              "application/xml" : {
                "schema" : {
                  "$ref" : "#/components/schemas/Warehouse"
                }
              }
            }
          }
        }
      }
    },
    "/v1.0/warehouses/by-externalReferenceCode/{externalReferenceCode}" : {
      "get" : {
        "tags" : [ "Warehouse" ],
        "operationId" : "getWarehouseByExternalReferenceCode",
        "parameters" : [ {
          "name" : "externalReferenceCode",
          "in" : "path",
          "required" : true,
          "schema" : {
            "type" : "string"
          }
        } ],
        "responses" : {
          "default" : {
            "description" : "default response",
            "content" : {
              "application/json" : {
                "schema" : {
                  "$ref" : "#/components/schemas/Warehouse"
                }
              },
              "application/xml" : {
                "schema" : {
                  "$ref" : "#/components/schemas/Warehouse"
                }
              }
            }
          }
        }
      },
      "put" : {
        "tags" : [ "Warehouse" ],
        "operationId" : "putWarehouseByExternalReferenceCode",
        "parameters" : [ {
          "name" : "externalReferenceCode",
          "in" : "path",
          "required" : true,
          "schema" : {
            "type" : "string"
          }
        } ],
        "requestBody" : {
          "content" : {
            "application/json" : {
              "schema" : {
                "$ref" : "#/components/schemas/Warehouse"
              }
            },
            "application/xml" : {
              "schema" : {
                "$ref" : "#/components/schemas/Warehouse"
              }
            }
          }
        },
        "responses" : {
          "default" : {
            "description" : "default response",
            "content" : {
              "application/json" : {
                "schema" : {
                  "$ref" : "#/components/schemas/Warehouse"
                }
              },
              "application/xml" : {
                "schema" : {
                  "$ref" : "#/components/schemas/Warehouse"
                }
              }
            }
          }
        }
      },
      "delete" : {
        "tags" : [ "Warehouse" ],
        "operationId" : "deleteWarehouseByExternalReferenceCode",
        "parameters" : [ {
          "name" : "externalReferenceCode",
          "in" : "path",
          "required" : true,
          "schema" : {
            "type" : "string"
          }
        } ],
        "responses" : {
          "default" : {
            "description" : "default response",
            "content" : {
              "application/json" : { },
              "application/xml" : { }
            }
          }
        }
      },
      "patch" : {
        "tags" : [ "Warehouse" ],
        "operationId" : "patchWarehouseByExternalReferenceCode",
        "parameters" : [ {
          "name" : "externalReferenceCode",
          "in" : "path",
          "required" : true,
          "schema" : {
            "type" : "string"
          }
        } ],
        "requestBody" : {
          "content" : {
            "application/json" : {
              "schema" : {
                "$ref" : "#/components/schemas/Warehouse"
              }
            },
            "application/xml" : {
              "schema" : {
                "$ref" : "#/components/schemas/Warehouse"
              }
            }
          }
        },
        "responses" : {
          "default" : {
            "description" : "default response",
            "content" : {
              "application/json" : { },
              "application/xml" : { }
            }
          }
        }
      }
    },
    "/v1.0/warehouses/batch" : {
      "post" : {
        "tags" : [ "Warehouse" ],
        "operationId" : "postWarehouseBatch",
        "parameters" : [ {
          "name" : "callbackURL",
          "in" : "query",
          "schema" : {
            "type" : "string"
          }
        } ],
        "requestBody" : {
          "content" : {
            "application/json" : {
              "schema" : {
                "type" : "object"
              }
            }
          }
        },
        "responses" : {
          "default" : {
            "description" : "default response",
            "content" : {
              "application/json" : { }
            }
          }
        }
      }
    },
    "/v1.0/warehouses/export-batch" : {
      "post" : {
        "tags" : [ "Warehouse" ],
        "operationId" : "postWarehousesPageExportBatch",
        "parameters" : [ {
          "name" : "filter",
          "in" : "query",
          "schema" : {
            "type" : "string"
          }
        }, {
          "name" : "search",
          "in" : "query",
          "schema" : {
            "type" : "string"
          }
        }, {
          "name" : "sort",
          "in" : "query",
          "schema" : {
            "type" : "string"
          }
        }, {
          "name" : "callbackURL",
          "in" : "query",
          "schema" : {
            "type" : "string"
          }
        }, {
          "name" : "contentType",
          "in" : "query",
          "schema" : {
            "type" : "string"
          }
        }, {
          "name" : "fieldNames",
          "in" : "query",
          "schema" : {
            "type" : "string"
          }
        } ],
        "responses" : {
          "default" : {
            "description" : "default response",
            "content" : {
              "application/json" : { }
            }
          }
        }
      }
    }
  },
  "components" : {
    "schemas" : {
      "AccountGroup" : {
        "type" : "object",
        "properties" : {
          "id" : {
            "type" : "integer",
            "format" : "int64",
            "readOnly" : true,
            "example" : 30130
          },
          "name" : {
            "type" : "string",
            "example" : "AccountGroup Name"
          },
          "x-class-name" : {
            "type" : "string",
            "readOnly" : true,
            "default" : "com.liferay.headless.commerce.admin.inventory.dto.v1_0.AccountGroup"
          }
        },
        "xml" : {
          "name" : "AccountGroup"
        }
      },
      "Account" : {
        "type" : "object",
        "properties" : {
          "id" : {
            "type" : "integer",
            "format" : "int64",
            "example" : 30130
          },
          "logoId" : {
            "type" : "integer",
            "format" : "int64",
            "example" : 20078
          },
          "name" : {
            "type" : "string",
            "example" : "Account Name"
          },
          "x-class-name" : {
            "type" : "string",
            "readOnly" : true,
            "default" : "com.liferay.headless.commerce.admin.inventory.dto.v1_0.Account"
          }
        },
        "xml" : {
          "name" : "Account"
        }
      },
      "Channel" : {
        "type" : "object",
        "properties" : {
          "currencyCode" : {
            "type" : "string"
          },
          "externalReferenceCode" : {
            "type" : "string"
          },
          "id" : {
            "type" : "integer",
            "format" : "int64"
          },
          "name" : {
            "type" : "string"
          },
          "siteGroupId" : {
            "type" : "integer",
            "format" : "int64"
          },
          "type" : {
            "type" : "string"
          },
          "x-class-name" : {
            "type" : "string",
            "readOnly" : true,
            "default" : "com.liferay.headless.commerce.admin.inventory.dto.v1_0.Channel"
          }
        },
        "xml" : {
          "name" : "Channel"
        }
      },
      "OrderType" : {
        "type" : "object",
        "properties" : {
          "id" : {
            "type" : "integer",
            "format" : "int64",
            "readOnly" : true,
            "example" : 30130
          },
          "name" : {
            "type" : "object",
            "additionalProperties" : {
              "type" : "string",
              "example" : "{en_US=Hand Saw, hr_HR=Product Name HR, hu_HU=Product Name HU}"
            },
            "example" : "{en_US=Hand Saw, hr_HR=Product Name HR, hu_HU=Product Name HU}"
          },
          "x-class-name" : {
            "type" : "string",
            "readOnly" : true,
            "default" : "com.liferay.headless.commerce.admin.inventory.dto.v1_0.OrderType"
          }
        },
        "xml" : {
          "name" : "OrderType"
        }
      },
      "ReplenishmentItem" : {
        "type" : "object",
        "properties" : {
          "availabilityDate" : {
            "type" : "string",
            "format" : "date-time"
          },
          "externalReferenceCode" : {
            "type" : "string",
            "example" : "AB-34098-789-N"
          },
          "id" : {
            "type" : "integer",
            "format" : "int64",
            "example" : 30130
          },
          "quantity" : {
            "type" : "number",
            "example" : 10.1
          },
          "sku" : {
            "type" : "string",
            "example" : "SKU"
          },
          "unitOfMeasureKey" : {
            "type" : "string",
            "example" : "lt"
          },
          "warehouseId" : {
            "type" : "integer",
            "format" : "int64",
            "example" : 30130
          },
          "x-class-name" : {
            "type" : "string",
            "readOnly" : true,
            "default" : "com.liferay.headless.commerce.admin.inventory.dto.v1_0.ReplenishmentItem"
          }
        },
        "xml" : {
          "name" : "ReplenishmentItem"
        }
      },
      "Facet" : {
        "type" : "object",
        "properties" : {
          "facetCriteria" : {
            "type" : "string"
          },
          "facetValues" : {
            "type" : "array",
            "items" : {
              "$ref" : "#/components/schemas/FacetValue"
            }
          }
        }
      },
      "FacetValue" : {
        "type" : "object",
        "properties" : {
          "numberOfOccurrences" : {
            "type" : "integer",
            "format" : "int32"
          },
          "term" : {
            "type" : "string"
          }
        }
      },
      "PageReplenishmentItem" : {
        "type" : "object",
        "properties" : {
          "lastPage" : {
            "type" : "integer",
            "format" : "int64"
          },
          "totalCount" : {
            "type" : "integer",
            "format" : "int64"
          },
          "items" : {
            "type" : "array",
            "items" : {
              "$ref" : "#/components/schemas/ReplenishmentItem"
            }
          },
          "pageSize" : {
            "type" : "integer",
            "format" : "int64"
          },
          "page" : {
            "type" : "integer",
            "format" : "int64"
          },
          "facets" : {
            "type" : "array",
            "items" : {
              "$ref" : "#/components/schemas/Facet"
            }
          },
          "actions" : {
            "type" : "object",
            "additionalProperties" : {
              "type" : "object",
              "additionalProperties" : {
                "type" : "string"
              }
            }
          }
        }
      },
      "WarehouseAccountGroup" : {
        "required" : [ "accountGroupId", "warehouseId" ],
        "type" : "object",
        "properties" : {
          "accountGroup" : {
            "$ref" : "#/components/schemas/AccountGroup"
          },
          "accountGroupExternalReferenceCode" : {
            "type" : "string",
            "example" : "DAB-34098-789-N"
          },
          "accountGroupId" : {
            "type" : "integer",
            "format" : "int64",
            "example" : 30324
          },
          "actions" : {
            "type" : "object",
            "additionalProperties" : {
              "type" : "object",
              "additionalProperties" : {
                "type" : "string"
              }
            },
            "readOnly" : true
          },
          "warehouseAccountGroupId" : {
            "type" : "integer",
            "format" : "int64",
            "readOnly" : true,
            "example" : 30643
          },
          "warehouseExternalReferenceCode" : {
            "type" : "string",
            "example" : "PAB-34098-789-N"
          },
          "warehouseId" : {
            "type" : "integer",
            "format" : "int64",
            "example" : 30130
          },
          "x-class-name" : {
            "type" : "string",
            "readOnly" : true,
            "default" : "com.liferay.headless.commerce.admin.inventory.dto.v1_0.WarehouseAccountGroup"
          }
        },
        "xml" : {
          "name" : "WarehouseAccountGroup"
        }
      },
      "PageWarehouseAccountGroup" : {
        "type" : "object",
        "properties" : {
          "lastPage" : {
            "type" : "integer",
            "format" : "int64"
          },
          "totalCount" : {
            "type" : "integer",
            "format" : "int64"
          },
          "items" : {
            "type" : "array",
            "items" : {
              "$ref" : "#/components/schemas/WarehouseAccountGroup"
            }
          },
          "pageSize" : {
            "type" : "integer",
            "format" : "int64"
          },
          "page" : {
            "type" : "integer",
            "format" : "int64"
          },
          "facets" : {
            "type" : "array",
            "items" : {
              "$ref" : "#/components/schemas/Facet"
            }
          },
          "actions" : {
            "type" : "object",
            "additionalProperties" : {
              "type" : "object",
              "additionalProperties" : {
                "type" : "string"
              }
            }
          }
        }
      },
      "WarehouseAccount" : {
        "required" : [ "accountId", "warehouseId" ],
        "type" : "object",
        "properties" : {
          "account" : {
            "$ref" : "#/components/schemas/Account"
          },
          "accountExternalReferenceCode" : {
            "type" : "string",
            "example" : "DAB-34098-789-N"
          },
          "accountId" : {
            "type" : "integer",
            "format" : "int64",
            "example" : 30324
          },
          "actions" : {
            "type" : "object",
            "additionalProperties" : {
              "type" : "object",
              "additionalProperties" : {
                "type" : "string"
              }
            },
            "readOnly" : true
          },
          "warehouseAccountId" : {
            "type" : "integer",
            "format" : "int64",
            "readOnly" : true,
            "example" : 30643
          },
          "warehouseExternalReferenceCode" : {
            "type" : "string",
            "example" : "PAB-34098-789-N"
          },
          "warehouseId" : {
            "type" : "integer",
            "format" : "int64",
            "example" : 30130
          },
          "x-class-name" : {
            "type" : "string",
            "readOnly" : true,
            "default" : "com.liferay.headless.commerce.admin.inventory.dto.v1_0.WarehouseAccount"
          }
        },
        "xml" : {
          "name" : "WarehouseAccount"
        }
      },
      "PageWarehouseAccount" : {
        "type" : "object",
        "properties" : {
          "lastPage" : {
            "type" : "integer",
            "format" : "int64"
          },
          "totalCount" : {
            "type" : "integer",
            "format" : "int64"
          },
          "items" : {
            "type" : "array",
            "items" : {
              "$ref" : "#/components/schemas/WarehouseAccount"
            }
          },
          "pageSize" : {
            "type" : "integer",
            "format" : "int64"
          },
          "page" : {
            "type" : "integer",
            "format" : "int64"
          },
          "facets" : {
            "type" : "array",
            "items" : {
              "$ref" : "#/components/schemas/Facet"
            }
          },
          "actions" : {
            "type" : "object",
            "additionalProperties" : {
              "type" : "object",
              "additionalProperties" : {
                "type" : "string"
              }
            }
          }
        }
      },
      "WarehouseChannel" : {
        "required" : [ "channelId", "warehouseId" ],
        "type" : "object",
        "properties" : {
          "actions" : {
            "type" : "object",
            "additionalProperties" : {
              "type" : "object",
              "additionalProperties" : {
                "type" : "string"
              }
            },
            "readOnly" : true
          },
          "channel" : {
            "$ref" : "#/components/schemas/Channel"
          },
          "channelExternalReferenceCode" : {
            "type" : "string",
            "example" : "PAB-34098-789-N"
          },
          "channelId" : {
            "type" : "integer",
            "format" : "int64",
            "example" : 30130
          },
          "warehouseChannelId" : {
            "type" : "integer",
            "format" : "int64",
            "readOnly" : true,
            "example" : 30643
          },
          "warehouseExternalReferenceCode" : {
            "type" : "string",
            "example" : "DAB-34098-789-N"
          },
          "warehouseId" : {
            "type" : "integer",
            "format" : "int64",
            "example" : 30324
          },
          "x-class-name" : {
            "type" : "string",
            "readOnly" : true,
            "default" : "com.liferay.headless.commerce.admin.inventory.dto.v1_0.WarehouseChannel"
          }
        },
        "xml" : {
          "name" : "WarehouseChannel"
        }
      },
      "PageWarehouseChannel" : {
        "type" : "object",
        "properties" : {
          "lastPage" : {
            "type" : "integer",
            "format" : "int64"
          },
          "totalCount" : {
            "type" : "integer",
            "format" : "int64"
          },
          "items" : {
            "type" : "array",
            "items" : {
              "$ref" : "#/components/schemas/WarehouseChannel"
            }
          },
          "pageSize" : {
            "type" : "integer",
            "format" : "int64"
          },
          "page" : {
            "type" : "integer",
            "format" : "int64"
          },
          "facets" : {
            "type" : "array",
            "items" : {
              "$ref" : "#/components/schemas/Facet"
            }
          },
          "actions" : {
            "type" : "object",
            "additionalProperties" : {
              "type" : "object",
              "additionalProperties" : {
                "type" : "string"
              }
            }
          }
        }
      },
      "WarehouseItem" : {
        "type" : "object",
        "properties" : {
          "externalReferenceCode" : {
            "type" : "string",
            "example" : "AB-34098-789-N"
          },
          "id" : {
            "type" : "integer",
            "format" : "int64",
            "example" : 30130
          },
          "modifiedDate" : {
            "type" : "string",
            "format" : "date-time"
          },
          "quantity" : {
            "minimum" : 0,
            "exclusiveMinimum" : false,
            "type" : "number",
            "example" : 1.1
          },
          "reservedQuantity" : {
            "minimum" : 0,
            "exclusiveMinimum" : false,
            "type" : "number",
            "example" : 2.1
          },
          "sku" : {
            "type" : "string",
            "example" : "SKU"
          },
          "unitOfMeasureKey" : {
            "type" : "string",
            "example" : "lt"
          },
          "warehouseExternalReferenceCode" : {
            "type" : "string",
            "example" : "AB-34098-789-N"
          },
          "warehouseId" : {
            "type" : "integer",
            "format" : "int64",
            "example" : 30030
          },
          "x-class-name" : {
            "type" : "string",
            "readOnly" : true,
            "default" : "com.liferay.headless.commerce.admin.inventory.dto.v1_0.WarehouseItem"
          }
        },
        "xml" : {
          "name" : "WarehouseItem"
        }
      },
      "PageWarehouseItem" : {
        "type" : "object",
        "properties" : {
          "lastPage" : {
            "type" : "integer",
            "format" : "int64"
          },
          "totalCount" : {
            "type" : "integer",
            "format" : "int64"
          },
          "items" : {
            "type" : "array",
            "items" : {
              "$ref" : "#/components/schemas/WarehouseItem"
            }
          },
          "pageSize" : {
            "type" : "integer",
            "format" : "int64"
          },
          "page" : {
            "type" : "integer",
            "format" : "int64"
          },
          "facets" : {
            "type" : "array",
            "items" : {
              "$ref" : "#/components/schemas/Facet"
            }
          },
          "actions" : {
            "type" : "object",
            "additionalProperties" : {
              "type" : "object",
              "additionalProperties" : {
                "type" : "string"
              }
            }
          }
        }
      },
      "WarehouseOrderType" : {
        "required" : [ "orderTypeId", "warehouseId" ],
        "type" : "object",
        "properties" : {
          "actions" : {
            "type" : "object",
            "additionalProperties" : {
              "type" : "object",
              "additionalProperties" : {
                "type" : "string"
              }
            },
            "readOnly" : true
          },
          "orderType" : {
            "$ref" : "#/components/schemas/OrderType"
          },
          "orderTypeExternalReferenceCode" : {
            "type" : "string",
            "example" : "DAB-34098-789-N"
          },
          "orderTypeId" : {
            "type" : "integer",
            "format" : "int64",
            "example" : 30324
          },
          "priority" : {
            "type" : "integer",
            "format" : "int32",
            "example" : 1
          },
          "warehouseExternalReferenceCode" : {
            "type" : "string",
            "example" : "PAB-34098-789-N"
          },
          "warehouseId" : {
            "type" : "integer",
            "format" : "int64",
            "example" : 30130
          },
          "warehouseOrderTypeId" : {
            "type" : "integer",
            "format" : "int64",
            "readOnly" : true,
            "example" : 30643
          },
          "x-class-name" : {
            "type" : "string",
            "readOnly" : true,
            "default" : "com.liferay.headless.commerce.admin.inventory.dto.v1_0.WarehouseOrderType"
          }
        },
        "xml" : {
          "name" : "WarehouseOrderType"
        }
      },
      "PageWarehouseOrderType" : {
        "type" : "object",
        "properties" : {
          "lastPage" : {
            "type" : "integer",
            "format" : "int64"
          },
          "totalCount" : {
            "type" : "integer",
            "format" : "int64"
          },
          "items" : {
            "type" : "array",
            "items" : {
              "$ref" : "#/components/schemas/WarehouseOrderType"
            }
          },
          "pageSize" : {
            "type" : "integer",
            "format" : "int64"
          },
          "page" : {
            "type" : "integer",
            "format" : "int64"
          },
          "facets" : {
            "type" : "array",
            "items" : {
              "$ref" : "#/components/schemas/Facet"
            }
          },
          "actions" : {
            "type" : "object",
            "additionalProperties" : {
              "type" : "object",
              "additionalProperties" : {
                "type" : "string"
              }
            }
          }
        }
      },
      "Warehouse" : {
        "type" : "object",
        "properties" : {
          "actions" : {
            "type" : "object",
            "additionalProperties" : {
              "type" : "object",
              "additionalProperties" : {
                "type" : "string"
              }
            },
            "readOnly" : true
          },
          "active" : {
            "type" : "boolean",
            "example" : true
          },
          "city" : {
            "type" : "string",
            "example" : "Diamond Bar"
          },
          "countryISOCode" : {
            "type" : "string",
            "example" : "US"
          },
          "description" : {
            "type" : "object",
            "additionalProperties" : {
              "type" : "string",
              "example" : "{en_US=Warehouse Description US, hr_HR=Warehouse Description HR, hu_HU=Warehouse Description HU}"
            },
            "example" : "{en_US=Warehouse Description US, hr_HR=Warehouse Description HR, hu_HU=Warehouse Description HU}"
          },
          "externalReferenceCode" : {
            "type" : "string",
            "example" : "AB-34098-789-N"
          },
          "id" : {
            "type" : "integer",
            "format" : "int64",
            "example" : 30130
          },
          "latitude" : {
            "type" : "number",
            "format" : "double",
            "example" : 33.9976884
          },
          "longitude" : {
            "type" : "number",
            "format" : "double",
            "example" : -117.8144595
          },
          "name" : {
            "type" : "object",
            "additionalProperties" : {
              "type" : "string",
              "example" : "{en_US=Warehouse Name US, hr_HR=Warehouse Name HR, hu_HU=Warehouse Name HU}"
            },
            "example" : "{en_US=Warehouse Name US, hr_HR=Warehouse Name HR, hu_HU=Warehouse Name HU}"
          },
          "regionISOCode" : {
            "type" : "string",
            "example" : "CA"
          },
          "street1" : {
            "type" : "string",
            "example" : "1400"
          },
          "street2" : {
            "type" : "string",
            "example" : "1st floor"
          },
          "street3" : {
            "type" : "string",
            "example" : "suite 200"
          },
          "type" : {
            "type" : "string"
          },
          "warehouseItems" : {
            "type" : "array",
            "items" : {
              "$ref" : "#/components/schemas/WarehouseItem"
            }
          },
          "zip" : {
            "type" : "string",
            "example" : "91765"
          },
          "x-class-name" : {
            "type" : "string",
            "readOnly" : true,
            "default" : "com.liferay.headless.commerce.admin.inventory.dto.v1_0.Warehouse"
          }
        },
        "xml" : {
          "name" : "Warehouse"
        }
      },
      "PageWarehouse" : {
        "type" : "object",
        "properties" : {
          "lastPage" : {
            "type" : "integer",
            "format" : "int64"
          },
          "totalCount" : {
            "type" : "integer",
            "format" : "int64"
          },
          "items" : {
            "type" : "array",
            "items" : {
              "$ref" : "#/components/schemas/Warehouse"
            }
          },
          "pageSize" : {
            "type" : "integer",
            "format" : "int64"
          },
          "page" : {
            "type" : "integer",
            "format" : "int64"
          },
          "facets" : {
            "type" : "array",
            "items" : {
              "$ref" : "#/components/schemas/Facet"
            }
          },
          "actions" : {
            "type" : "object",
            "additionalProperties" : {
              "type" : "object",
              "additionalProperties" : {
                "type" : "string"
              }
            }
          }
        }
      }
    }
  }
}